PytorchRengongzhinengJichuzhishiChuyiFix1/README.md
PytorchRengongzhinengJichuzhishiChuyiFix1/__init__.py
PytorchRengongzhinengJichuzhishiChuyiFix1/__main__.py
PytorchRengongzhinengJichuzhishiChuyiFix1/file.epub
PytorchRengongzhinengJichuzhishiChuyiFix1/index.html
PytorchRengongzhinengJichuzhishiChuyiFix1/css/__init__.py
PytorchRengongzhinengJichuzhishiChuyiFix1/css/annotations.css
PytorchRengongzhinengJichuzhishiChuyiFix1/css/main.css
PytorchRengongzhinengJichuzhishiChuyiFix1/css/normalize.css
PytorchRengongzhinengJichuzhishiChuyiFix1/css/popup.css
PytorchRengongzhinengJichuzhishiChuyiFix1/font/__init__.py
PytorchRengongzhinengJichuzhishiChuyiFix1/font/fontello.eot
PytorchRengongzhinengJichuzhishiChuyiFix1/font/fontello.svg
PytorchRengongzhinengJichuzhishiChuyiFix1/font/fontello.ttf
PytorchRengongzhinengJichuzhishiChuyiFix1/font/fontello.woff
PytorchRengongzhinengJichuzhishiChuyiFix1/img/__init__.py
PytorchRengongzhinengJichuzhishiChuyiFix1/img/annotator-glyph-sprite.png
PytorchRengongzhinengJichuzhishiChuyiFix1/img/annotator-icon-sprite.png
PytorchRengongzhinengJichuzhishiChuyiFix1/img/apple-touch-icon.png
PytorchRengongzhinengJichuzhishiChuyiFix1/img/cancelfullscreen.png
PytorchRengongzhinengJichuzhishiChuyiFix1/img/close.png
PytorchRengongzhinengJichuzhishiChuyiFix1/img/fullscreen.png
PytorchRengongzhinengJichuzhishiChuyiFix1/img/loader.gif
PytorchRengongzhinengJichuzhishiChuyiFix1/img/menu-icon.png
PytorchRengongzhinengJichuzhishiChuyiFix1/img/save.png
PytorchRengongzhinengJichuzhishiChuyiFix1/img/saved.png
PytorchRengongzhinengJichuzhishiChuyiFix1/img/settings-s.png
PytorchRengongzhinengJichuzhishiChuyiFix1/img/settings.png
PytorchRengongzhinengJichuzhishiChuyiFix1/img/star.png
PytorchRengongzhinengJichuzhishiChuyiFix1/js/__init__.py
PytorchRengongzhinengJichuzhishiChuyiFix1/js/epub.js
PytorchRengongzhinengJichuzhishiChuyiFix1/js/epub.min.js
PytorchRengongzhinengJichuzhishiChuyiFix1/js/epub.min.map
PytorchRengongzhinengJichuzhishiChuyiFix1/js/hooks.min.js
pytorch_rengongzhineng_jichuzhishi_chuyi_fix1-2025.3.25.0.dist-info/METADATA
pytorch_rengongzhineng_jichuzhishi_chuyi_fix1-2025.3.25.0.dist-info/WHEEL
pytorch_rengongzhineng_jichuzhishi_chuyi_fix1-2025.3.25.0.dist-info/entry_points.txt
pytorch_rengongzhineng_jichuzhishi_chuyi_fix1-2025.3.25.0.dist-info/top_level.txt
pytorch_rengongzhineng_jichuzhishi_chuyi_fix1-2025.3.25.0.dist-info/RECORD
